dwm_status_bar/__init__.py
dwm_status_bar/__main__.py
dwm_status_bar/app.py
dwm_status_bar/config.py
dwm_status_bar/methods.py
dwm_status_bar/util.py
dwm_status_bar/x11.py
dwm_status_bar/modules/base_module.py
dwm_status_bar/modules/battery_module.py
dwm_status_bar/modules/cpu_module.py
dwm_status_bar/modules/datetime_module.py
dwm_status_bar/modules/disk_module.py
dwm_status_bar/modules/ram_module.py
dwm_status_bar-0.3.2.dist-info/METADATA
dwm_status_bar-0.3.2.dist-info/WHEEL
dwm_status_bar-0.3.2.dist-info/entry_points.txt
dwm_status_bar-0.3.2.dist-info/RECORD
