Metadata-Version: 2.4
Name: dwm_status_bar
Version: 0.3.2
Summary: Add status information to your Dynamic Window Manager bar
Project-URL: Homepage, https://github.com/llucasls/dwm-status-bar
Author-email: "Lucas L. S. Haine" <lucaslshaine@gmail.com>
Classifier: License :: OSI Approved :: MIT License
Classifier: Operating System :: POSIX
Classifier: Programming Language :: Python :: 3
Requires-Python: >=3.8
Requires-Dist: psutil
